hivemind_ggwave/__init__.py
hivemind_ggwave/version.py
hivemind_ggwave-0.0.1.dist-info/LICENSE.md
hivemind_ggwave-0.0.1.dist-info/METADATA
hivemind_ggwave-0.0.1.dist-info/WHEEL
hivemind_ggwave-0.0.1.dist-info/top_level.txt
hivemind_ggwave-0.0.1.dist-info/RECORD
