Metadata-Version: 2.1
Name: hivemind-ggwave
Version: 0.0.1
Summary: data over sound for hivemind
Home-page: https://github.com/JarbasHiveMind/hivemind-ggwave
Author: jarbasAi
Author-email: jarbasai@mailfence.com
License: Apache-2.0
Platform: UNKNOWN
Requires-Dist: pexpect
Requires-Dist: requests
Requires-Dist: hivemind-bus-client
Requires-Dist: ovos-utils
